LICENSE
MANIFEST.in
README.txt
setup.py
atomisator/__init__.py
atomisator.feed.egg-info/PKG-INFO
atomisator.feed.egg-info/SOURCES.txt
atomisator.feed.egg-info/dependency_links.txt
atomisator.feed.egg-info/entry_points.txt
atomisator.feed.egg-info/namespace_packages.txt
atomisator.feed.egg-info/not-zip-safe
atomisator.feed.egg-info/requires.txt
atomisator.feed.egg-info/top_level.txt
atomisator/feed/__init__.py
atomisator/feed/rss2.tmpl
atomisator/feed/docs/README.txt
atomisator/feed/tests/__init__.py
atomisator/feed/tests/test_docs.py