Metadata-Version: 1.0
Name: atomisator.feed
Version: 0.3.1
Summary: Expert Python Programming - Feed generator
Home-page: http://atomisator.ziade.org
Author: Tarek Ziade
Author-email: tarek@ziade.org
License: GPL
Platform: UNKNOWN
Classifier: Programming Language :: Python
Classifier: Topic :: Software Development :: Libraries :: Python Modules
